README.rst
setup.py
classsettings/__init__.py
classsettings/env.py
classsettings/settings.py
classsettings/urls.py
classsettings/utils.py
django_classsettings.egg-info/PKG-INFO
django_classsettings.egg-info/SOURCES.txt
django_classsettings.egg-info/dependency_links.txt
django_classsettings.egg-info/requires.txt
django_classsettings.egg-info/top_level.txt
django_classsettings.egg-info/zip-safe