Metadata-Version: 1.1
Name: django-classsettings
Version: 1.0.2
Summary: Adds ability to define Django settings with classes/functions and navigate each of them easily
Home-page: https://github.com/dferens/django-classsettings
Author: Dmitriy Ferens
Author-email: ferensdima@gmail.com
License: MIT
Download-URL: https://pypi.python.org/pypi/django-classsettings
Platform: Any
Classifier: Development Status :: 2 - Pre-Alpha
Classifier: Framework :: Django
Classifier: Intended Audience :: Developers
Classifier: Natural Language :: English
Classifier: License :: OSI Approved :: MIT License
Classifier: Operating System :: OS Independent
Classifier: Programming Language :: Python
Classifier: Programming Language :: Python :: 2
Classifier: Programming Language :: Python :: 2.6
Classifier: Programming Language :: Python :: 2.7
Classifier: Programming Language :: Python :: 3
Classifier: Programming Language :: Python :: 3.2
Classifier: Programming Language :: Python :: 3.3
Classifier: Topic :: Software Development :: Libraries :: Python Modules
